<?xml version="1.0" encoding="UTF-8"?>
<counties>
    <county>
        <name>宛县</name>
        <feature/>
        <feature_type>pref_seat</feature_type>
    </county>
    <county>
        <name>宛县</name>
        <feature>屈申城</feature>
        <feature_type>walled</feature_type>
    </county>
    <county>
        <name>宛县</name>
        <feature>北筮山</feature>
        <feature_type>mount</feature_type>
    </county>
    <county>
        <name>宛县</name>
        <feature>工官</feature>
        <feature_type>admin</feature_type>
    </county>
    <county>
        <name>宛县</name>
        <feature>铁官</feature>
        <feature_type>resource</feature_type>
    </county>
    <county>
        <name>育阳县</name>
        <feature>南筮聚</feature>
        <feature_type>sett</feature_type>
    </county>
    <county>
        <name>雉县</name>
        <feature>衡山</feature>
        <feature_type>river_source</feature_type>
    </county>
    <county>
        <name>雉县</name>
        <feature>沣水</feature>
        <feature_type>river</feature_type>
    </county>
    <county>
        <name>蔡阳县</name>
        <feature>功显君邑</feature>
        <feature_type>fief</feature_type>
    </county>
    <county>
        <name>舞阴县</name>
        <feature>中阴山</feature>
        <feature_type>river_source</feature_type>
    </county>
    <county>
        <name>舞阴县</name>
        <feature>瀙水</feature>
        <feature_type>river</feature_type>
    </county>
    <county>
        <name>郦县</name>
        <feature>育水</feature>
        <feature_type>river</feature_type>
    </county>
    <county>
        <name>平氏县</name>
        <feature>桐柏大复山</feature>
        <feature_type>river_source</feature_type>
    </county>
    <county>
        <name>平氏县</name>
        <feature>淮水</feature>
        <feature_type>interPrefRiver</feature_type>
    </county>
    <county>
        <name>随县</name>
        <feature>厉乡</feature>
        <feature_type>sett</feature_type>
    </county>
    <county>
        <name>叶县</name>
        <feature>长城</feature>
        <feature_type>mili</feature_type>
    </county>
    <county>
        <name>邓县</name>
        <feature>都尉治</feature>
        <feature_type>mili_admin</feature_type>
    </county>
    <county>
        <name>鲁阳县</name>
        <feature>鲁山</feature>
        <feature_type>mount</feature_type>
    </county>
    <county>
        <name>鲁阳县</name>
        <feature>鲁山</feature>
        <feature_type>river_source</feature_type>
    </county>
    <county>
        <name>鲁阳县</name>
        <feature>滍水</feature>
        <feature_type>river</feature_type>
    </county>
    <county>
        <name>鲁阳县</name>
        <feature>昆水</feature>
        <feature_type>river</feature_type>
    </county>
    <county>
        <name>舂陵县</name>
        <feature>上唐乡</feature>
        <feature_type>sett</feature_type>
    </county>
</counties>
