<?xml version="1.0" encoding="UTF-8"?>
<counties>
    <county>
        <name>县</name>
        <feature>铁官</feature>
        <feature_type>resource</feature_type>
    </county>
    <county>
        <name>县</name>
        <feature>盐官</feature>
        <feature_type>resource</feature_type>
    </county>
    <county>
        <name>狄道县</name>
        <feature/>
        <feature_type>pref_seat</feature_type>
    </county>
    <county>
        <name>狄道县</name>
        <feature>白石山</feature>
        <feature_type>mount</feature_type>
    </county>
    <county>
        <name>氐道县</name>
        <feature>养水</feature>
        <feature_type>river</feature_type>
    </county>
    <county>
        <name>首阳县</name>
        <feature>鸟鼠同穴山</feature>
        <feature_type>mount</feature_type>
    </county>
    <county>
        <name>首阳县</name>
        <feature>渭水</feature>
        <feature_type>interPrefRiver</feature_type>
    </county>
    <county>
        <name>羌道县</name>
        <feature>羌水</feature>
        <feature_type>interPrefRiver</feature_type>
    </county>
    <county>
        <name>临洮县</name>
        <feature>洮水</feature>
        <feature_type>river</feature_type>
    </county>
    <county>
        <name>临洮县</name>
        <feature>西顷山</feature>
        <feature_type>mount</feature_type>
    </county>
    <county>
        <name>临洮县</name>
        <feature>南部都尉治</feature>
        <feature_type>mili_admin</feature_type>
    </county>
    <county>
        <name>西县</name>
        <feature>嶓冢山</feature>
        <feature_type>mount</feature_type>
    </county>
    <county>
        <name>西县</name>
        <feature>西汉</feature>
        <feature_type>interPrefRiver</feature_type>
    </county>
</counties>
